setup.py
apricotlib/__init__.py
apricotlib/annotate_selected_data.py
apricotlib/annotate_selected_data_without_uniprot.py
apricotlib/apricot_visualization.py
apricotlib/calculate_annotation_score.py
apricotlib/classify_selected_data.py
apricotlib/collect_uniprot_info_for_query.py
apricotlib/compile_selected_domains.py
apricotlib/convert_csv_format.py
apricotlib/create_analysis_summary.py
apricotlib/create_keyword_files.py
apricotlib/create_query_files.py
apricotlib/current_interpro_version.py
apricotlib/filter_keyword_selected_result.py
apricotlib/folder_setup.py
apricotlib/interpro_xml_to_table.py
apricotlib/keyword_based_domain_selection.py
apricotlib/keyword_selected_cdd_data.py
apricotlib/keyword_selected_cdd_domain.py
apricotlib/keyword_selected_ipr_data.py
apricotlib/keyword_selected_ipr_domain.py
apricotlib/list_similar_pdbstr.py
apricotlib/literature_secstr.py
apricotlib/map_domain_to_go.py
apricotlib/map_query_to_uniprot.py
apricotlib/psortb_localization.py
apricotlib/query_annotation_data.py
apricotlib/raptorx_secstr.py
apricotlib/rna_related_cdd_domain.py
apricotlib/rna_related_ipr_domain.py
apricotlib/sort_sec_struc_pdb_data.py
apricotlib/uniprot_proteome_table.py
apricotlib/uniprot_taxid.py
bin/apricot
bio_APRICOT.egg-info/PKG-INFO
bio_APRICOT.egg-info/SOURCES.txt
bio_APRICOT.egg-info/dependency_links.txt
bio_APRICOT.egg-info/requires.txt
bio_APRICOT.egg-info/top_level.txt