Metadata-Version: 1.1
Name: bio-APRICOT
Version: 1.2.1
Summary: Sequence-based identification and characterization of protein classes
Home-page: https://www.python.org/pypi/bio-apricot
Author: Malvika Sharan
Author-email: malvikasharan@gmail.com
License: ISC License (ISCL)
Platform: UNKNOWN
Classifier: License :: OSI Approved :: ISC License (ISCL)
Classifier: Operating System :: POSIX
Classifier: Programming Language :: Python :: 3
Classifier: Topic :: Scientific/Engineering :: Bio-Informatics
